cchdo/params/__init__.py
cchdo/params/__main__.py
cchdo/params/_cf_names.py
cchdo/params/_whp_names.py
cchdo/params/core.py
cchdo/params/db.py
cchdo/params/parameters.schema.json
cchdo/params/params.sqlite3
cchdo/params/params.sqlite3.sql
cchdo/params/py.typed
cchdo/params/test/conftest.py
cchdo/params/test/test_aliasing.py
cchdo/params/test/test_data.py
cchdo/params/test/test_ordering.py
cchdo_params-2025.4.0.dist-info/licenses/LICENSE.md
cchdo_params-2025.4.0.dist-info/METADATA
cchdo_params-2025.4.0.dist-info/WHEEL
cchdo_params-2025.4.0.dist-info/top_level.txt
cchdo_params-2025.4.0.dist-info/RECORD
