Metadata-Version: 2.4
Name: cchdo.params
Version: 2025.4.0
Author-email: cchdo <cchdo@ucsd.edu>
License-Expression: BSD-3-Clause
Project-URL: Homepage, https://cchdo.ucsd.edu/
Project-URL: Documentation, https://cchdo.github.io/params/
Project-URL: Repository, https://github.com/cchdo/params.git
Classifier: Development Status :: 5 - Production/Stable
Classifier: Intended Audience :: Science/Research
Classifier: Operating System :: OS Independent
Classifier: Programming Language :: Python
Classifier: Programming Language :: Python :: 3
Classifier: Programming Language :: Python :: 3.11
Classifier: Programming Language :: Python :: 3.12
Classifier: Topic :: Scientific/Engineering
Requires-Python: >=3.11
License-File: LICENSE.md
Provides-Extra: selftest
Requires-Dist: pytest; extra == "selftest"
Requires-Dist: jsonschema; extra == "selftest"
Requires-Dist: sqlalchemy; extra == "selftest"
Dynamic: license-file
